[
    {
        "appliedCrowdControlPerMinute": 2.003577817531306,
        "blockPerMinute": 11.091234347048301,
        "cleansesInPerMinute": 82.6118067978533,
        "deathPerMinute": 0.061951471347444505,
        "deathRatio": 11.11111111111111,
        "downPerMinute": 0.09292720702116676,
        "durationInCombat": 1677,
        "evadePerMinute": 2.6475849731663685,
        "id": "用爱感动坑逼.7495",
        "opScore": 0.0,
        "profession": "时空",
        "quicknessPerSecond": 0.2758524150268336,
        "regenerationUptime": 92.1752,
        "resPerMinute": 0.17889087656529518,
        "resistancePerSecond": 0.053327787716159814,
        "ripsInPerMinute": 6.726296958855099,
        "riteUptime": 24.9187,
        "score": 70.22964596681781,
        "stabilityPerSecond": 3.414509838998211,
        "surviveRatio": 86.57718120805369
    },
    {
        "appliedCrowdControlPerMinute": 0.8160851567120048,
        "blockPerMinute": 90.3725606150207,
        "cleansesInPerMinute": 76.88941454760497,
        "deathPerMinute": 0.061951471347444505,
        "deathRatio": 11.11111111111111,
        "downPerMinute": 0.09292720702116676,
        "durationInCombat": 1691,
        "evadePerMinute": 38.001182732111175,
        "id": "随便玩玩.8537",
        "opScore": 0.0,
        "profession": "诗人",
        "quicknessPerSecond": 0.22007007687758728,
        "regenerationUptime": 88.7064,
        "resPerMinute": 0.24837374334713186,
        "resistancePerSecond": 0.06576369012418687,
        "ripsInPerMinute": 1.2418687167356595,
        "riteUptime": 29.3415,
        "score": 96.28291171915333,
        "stabilityPerSecond": 3.590086930810171,
        "surviveRatio": 87.29994837377387
    },
    {
        "appliedCrowdControlPerMinute": 1.0194174757281553,
        "blockPerMinute": 45.0,
        "cleansesInPerMinute": 76.92961165048544,
        "deathPerMinute": 0.030975735673722252,
        "deathRatio": 5.555555555555555,
        "downPerMinute": 0.030975735673722252,
        "durationInCombat": 1648,
        "evadePerMinute": 41.504854368932044,
        "id": "猫爪加鲁鲁.6930",
        "opScore": 0.0,
        "profession": "诗人",
        "quicknessPerSecond": 0.14663452669902916,
        "regenerationUptime": 93.6074,
        "resPerMinute": 0.1820388349514563,
        "resistancePerSecond": 0.08576887135922331,
        "ripsInPerMinute": 1.0194174757281553,
        "riteUptime": 26.3547,
        "score": 93.2585600754783,
        "stabilityPerSecond": 4.022267597087379,
        "surviveRatio": 85.08002065049045
    },
    {
        "appliedCrowdControlPerMinute": 0.9101941747572816,
        "blockPerMinute": 44.67233009708738,
        "cleansesInPerMinute": 75.07281553398059,
        "deathPerMinute": 0.030975735673722252,
        "deathRatio": 5.555555555555555,
        "downPerMinute": 0.12390294269488901,
        "durationInCombat": 1648,
        "evadePerMinute": 21.444174757281555,
        "id": "开心小粽子.9021",
        "opScore": 0.0,
        "profession": "诗人",
        "quicknessPerSecond": 0.18716383495145633,
        "regenerationUptime": 89.0935,
        "resPerMinute": 0.8009708737864079,
        "resistancePerSecond": 0.08036195388349514,
        "ripsInPerMinute": 1.0922330097087378,
        "riteUptime": 26.6649,
        "score": 92.48286894268989,
        "stabilityPerSecond": 3.6958118932038837,
        "surviveRatio": 85.08002065049045
    },
    {
        "appliedCrowdControlPerMinute": 0.45161290322580644,
        "blockPerMinute": 56.96774193548387,
        "cleansesInPerMinute": 62.0,
        "deathPerMinute": 0.10416666666666667,
        "deathRatio": 16.666666666666668,
        "downPerMinute": 0.10416666666666667,
        "durationInCombat": 930,
        "evadePerMinute": 37.16129032258065,
        "id": "stan.1435",
        "opScore": 0.0,
        "profession": "诗人",
        "quicknessPerSecond": 0.1774756989247312,
        "regenerationUptime": 91.08839999999999,
        "resPerMinute": 0.6451612903225806,
        "resistancePerSecond": 0.05705623655913979,
        "ripsInPerMinute": 1.6774193548387097,
        "riteUptime": 24.8701,
        "score": 92.41412544802867,
        "stabilityPerSecond": 2.7405172043010757,
        "surviveRatio": 80.72916666666667
    },
    {
        "appliedCrowdControlPerMinute": 1.1244979919678715,
        "blockPerMinute": 85.50200803212851,
        "cleansesInPerMinute": 49.277108433734945,
        "deathPerMinute": 0.12390294269488901,
        "deathRatio": 22.22222222222222,
        "downPerMinute": 0.15487867836861127,
        "durationInCombat": 1494,
        "evadePerMinute": 31.68674698795181,
        "id": "浩雨林.2014",
        "opScore": 0.0,
        "profession": "诗人",
        "quicknessPerSecond": 0.1859901606425703,
        "regenerationUptime": 89.9597,
        "resPerMinute": 0.7630522088353414,
        "resistancePerSecond": 0.06985461847389557,
        "ripsInPerMinute": 1.1244979919678715,
        "riteUptime": 27.8591,
        "score": 89.68926886257819,
        "stabilityPerSecond": 2.808345381526104,
        "surviveRatio": 77.1295818275684
    },
    {
        "appliedCrowdControlPerMinute": 0.5360333531864204,
        "blockPerMinute": 68.54079809410364,
        "cleansesInPerMinute": 56.783799880881475,
        "deathPerMinute": 0.061951471347444505,
        "deathRatio": 11.11111111111111,
        "downPerMinute": 0.21683014971605577,
        "durationInCombat": 1679,
        "evadePerMinute": 22.156045265038713,
        "id": "东悦丶.1836",
        "opScore": 0.0,
        "profession": "诗人",
        "quicknessPerSecond": 0.17468743299583084,
        "regenerationUptime": 90.269,
        "resPerMinute": 1.1078022632519355,
        "resistancePerSecond": 0.05950023823704587,
        "ripsInPerMinute": 0.714711137581894,
        "riteUptime": 35.7539,
        "score": 88.89231813285866,
        "stabilityPerSecond": 3.1470315664085766,
        "surviveRatio": 86.68043366029943
    },
    {
        "appliedCrowdControlPerMinute": 0.4580152671755725,
        "blockPerMinute": 44.88549618320611,
        "cleansesInPerMinute": 46.10687022900763,
        "deathPerMinute": 0.0,
        "deathRatio": 0.0,
        "downPerMinute": 0.0,
        "durationInCombat": 393,
        "evadePerMinute": 12.51908396946565,
        "id": "对丶我就是D哥.8457",
        "opScore": 0.0,
        "profession": "诗人",
        "quicknessPerSecond": 0.15409185750636134,
        "regenerationUptime": 78.8713,
        "resPerMinute": 0.15267175572519084,
        "resistancePerSecond": 0.04075623409669212,
        "ripsInPerMinute": 0.3053435114503817,
        "riteUptime": 23.1008,
        "score": 88.24503180661577,
        "stabilityPerSecond": 2.330702290076336,
        "surviveRatio": 92.68867924528301
    },
    {
        "appliedCrowdControlPerMinute": 0.7019958706125259,
        "blockPerMinute": 64.99655884377151,
        "cleansesInPerMinute": 61.527873365450795,
        "deathPerMinute": 0.12390294269488901,
        "deathRatio": 22.22222222222222,
        "downPerMinute": 0.24780588538977802,
        "durationInCombat": 1453,
        "evadePerMinute": 17.673778389538885,
        "id": "地瓜丶.7925",
        "opScore": 0.0,
        "profession": "诗人",
        "quicknessPerSecond": 0.23396992429456295,
        "regenerationUptime": 85.5084,
        "resPerMinute": 0.2477632484514797,
        "resistancePerSecond": 0.0576025464556091,
        "ripsInPerMinute": 1.1149346180316586,
        "riteUptime": 21.1904,
        "score": 88.077133705767,
        "stabilityPerSecond": 2.6984053682037166,
        "surviveRatio": 75.01290655653072
    },
    {
        "appliedCrowdControlPerMinute": 0.6224066390041494,
        "blockPerMinute": 57.676348547717836,
        "cleansesInPerMinute": 64.52282157676348,
        "deathPerMinute": 0.06988934187536401,
        "deathRatio": 12.5,
        "downPerMinute": 0.13977868375072802,
        "durationInCombat": 1446,
        "evadePerMinute": 7.095435684647303,
        "id": "大灰狼.2538",
        "opScore": 0.0,
        "profession": "诗人",
        "quicknessPerSecond": 0.15856708160442598,
        "regenerationUptime": 82.258,
        "resPerMinute": 0.49792531120331945,
        "resistancePerSecond": 0.03520159059474413,
        "ripsInPerMinute": 1.3692946058091287,
        "riteUptime": 23.0352,
        "score": 85.9051412622346,
        "stabilityPerSecond": 2.1905636237897648,
        "surviveRatio": 84.21665695981363
    },
    {
        "appliedCrowdControlPerMinute": 3.693379790940767,
        "blockPerMinute": 53.76306620209059,
        "cleansesInPerMinute": 9.512195121951219,
        "deathPerMinute": 0.030975735673722252,
        "deathRatio": 5.555555555555555,
        "downPerMinute": 0.2787816210635003,
        "durationInCombat": 1722,
        "evadePerMinute": 160.03484320557493,
        "id": "安静不言语.6239",
        "pin":true,
        "opScore": 0.0,
        "profession": "诗人",
        "quicknessPerSecond": 0.0,
        "regenerationUptime": 87.9106,
        "resPerMinute": 0.8710801393728224,
        "resistancePerSecond": 0.0278979094076655,
        "ripsInPerMinute": 7.7700348432055755,
        "riteUptime": 23.6094,
        "score": 50.564356527959404,
        "stabilityPerSecond": 0.7695383275261324,
        "surviveRatio": 88.90036138358286
    },
    {
        "appliedCrowdControlPerMinute": 4.590747330960854,
        "blockPerMinute": 79.7864768683274,
        "cleansesInPerMinute": 54.44839857651245,
        "deathPerMinute": 0.030975735673722252,
        "deathRatio": 5.555555555555555,
        "downPerMinute": 0.061951471347444505,
        "durationInCombat": 1686,
        "evadePerMinute": 184.62633451957294,
        "id": "Suver.3791",
        "opScore": 0.0,
        "profession": "裁决",
        "quicknessPerSecond": 0.0,
        "regenerationUptime": 91.0464,
        "resPerMinute": 0.03558718861209964,
        "resistancePerSecond": 0.3561117437722419,
        "ripsInPerMinute": 23.701067615658364,
        "riteUptime": 36.4918,
        "score": 97.2621546692339,
        "stabilityPerSecond": 1.1768576512455515,
        "surviveRatio": 87.04181724315953
    },
    {
        "appliedCrowdControlPerMinute": 2.6865671641791042,
        "blockPerMinute": 47.46268656716418,
        "cleansesInPerMinute": 39.40298507462686,
        "deathPerMinute": 0.0,
        "deathRatio": 0.0,
        "downPerMinute": 0.0,
        "durationInCombat": 67,
        "evadePerMinute": 60.8955223880597,
        "id": "何小邪.8046",
        "opScore": 0.0,
        "profession": "裁决",
        "quicknessPerSecond": 0.0,
        "regenerationUptime": 98.407,
        "resPerMinute": 0.0,
        "resistancePerSecond": 0.24785074626865675,
        "ripsInPerMinute": 27.761194029850746,
        "riteUptime": 41.097,
        "score": 92.97087064676617,
        "stabilityPerSecond": 0.7746716417910448,
        "surviveRatio": 91.78082191780823
    },
    {
        "appliedCrowdControlPerMinute": 3.364485981308411,
        "blockPerMinute": 70.72017592083563,
        "cleansesInPerMinute": 30.41231445849368,
        "deathPerMinute": 0.0,
        "deathRatio": 0.0,
        "downPerMinute": 0.0,
        "durationInCombat": 1819,
        "evadePerMinute": 94.76635514018692,
        "id": "cczzyy.7649",
        "opScore": 0.0,
        "profession": "裁决",
        "quicknessPerSecond": 0.0,
        "regenerationUptime": 92.0073,
        "resPerMinute": 0.32985156679494226,
        "resistancePerSecond": 0.23623007146783942,
        "ripsInPerMinute": 24.672897196261683,
        "riteUptime": 27.3926,
        "score": 89.84397347574544,
        "stabilityPerSecond": 0.3811017042330951,
        "surviveRatio": 93.9081053175013
    },
    {
        "appliedCrowdControlPerMinute": 1.8461538461538463,
        "blockPerMinute": 49.403076923076924,
        "cleansesInPerMinute": 35.409230769230774,
        "deathPerMinute": 0.09292720702116676,
        "deathRatio": 16.666666666666668,
        "downPerMinute": 0.18585441404233352,
        "durationInCombat": 1625,
        "evadePerMinute": 179.2246153846154,
        "id": "九成宫.3512",
        "opScore": 0.0,
        "profession": "裁决",
        "quicknessPerSecond": 0.0,
        "regenerationUptime": 91.1071,
        "resPerMinute": 0.25846153846153846,
        "resistancePerSecond": 0.3575913846153847,
        "ripsInPerMinute": 24.443076923076923,
        "riteUptime": 30.94,
        "score": 89.69013113061435,
        "stabilityPerSecond": 1.2292129230769233,
        "surviveRatio": 83.89261744966443
    },
    {
        "appliedCrowdControlPerMinute": 3.2321253672869736,
        "blockPerMinute": 34.37806072477963,
        "cleansesInPerMinute": 47.48285994123409,
        "deathPerMinute": 0.0,
        "deathRatio": 0.0,
        "downPerMinute": 0.0,
        "durationInCombat": 1021,
        "evadePerMinute": 114.47600391772772,
        "id": "fyy.7869",
        "opScore": 0.0,
        "profession": "裁决",
        "quicknessPerSecond": 0.0,
        "regenerationUptime": 88.9413,
        "resPerMinute": 0.0,
        "resistancePerSecond": 0.21854495592556314,
        "ripsInPerMinute": 25.798237022526937,
        "riteUptime": 21.4496,
        "score": 87.83523782472832,
        "stabilityPerSecond": 0.9711371204701272,
        "surviveRatio": 88.62847222222223
    },
    {
        "appliedCrowdControlPerMinute": 3.217665615141956,
        "blockPerMinute": 38.64984227129337,
        "cleansesInPerMinute": 40.656151419558356,
        "deathPerMinute": 0.061951471347444505,
        "deathRatio": 11.11111111111111,
        "downPerMinute": 0.09292720702116676,
        "durationInCombat": 1585,
        "evadePerMinute": 64.42902208201892,
        "id": "Inliz.8632",
        "opScore": 0.0,
        "profession": "裁决",
        "quicknessPerSecond": 0.0,
        "regenerationUptime": 89.4294,
        "resPerMinute": 0.22712933753943218,
        "resistancePerSecond": 0.32008132492113567,
        "ripsInPerMinute": 27.482649842271293,
        "riteUptime": 30.1296,
        "score": 86.61228657269095,
        "stabilityPerSecond": 0.5609148264984227,
        "surviveRatio": 81.82756840474961
    },
    {
        "appliedCrowdControlPerMinute": 5.444015444015444,
        "blockPerMinute": 69.76833976833977,
        "cleansesInPerMinute": 38.88030888030888,
        "deathPerMinute": 0.09292720702116676,
        "deathRatio": 16.666666666666668,
        "downPerMinute": 0.21683014971605577,
        "durationInCombat": 1554,
        "evadePerMinute": 159.53667953667954,
        "id": "raner.6405",
        "opScore": 0.0,
        "profession": "裁决",
        "quicknessPerSecond": 0.0,
        "regenerationUptime": 90.3063,
        "resPerMinute": 0.5405405405405406,
        "resistancePerSecond": 0.3434480694980695,
        "ripsInPerMinute": 30.733590733590734,
        "riteUptime": 27.0952,
        "score": 85.90592695859073,
        "stabilityPerSecond": 0.8192323037323036,
        "surviveRatio": 80.22715539494062
    },
    {
        "appliedCrowdControlPerMinute": 3.463203463203463,
        "blockPerMinute": 81.64502164502164,
        "cleansesInPerMinute": 26.017316017316016,
        "deathPerMinute": 0.17472335468841002,
        "deathRatio": 31.25,
        "downPerMinute": 0.27955736750145604,
        "durationInCombat": 1386,
        "evadePerMinute": 170.86580086580085,
        "id": "滑溜溜.6752",
        "opScore": 0.0,
        "profession": "裁决",
        "quicknessPerSecond": 0.0,
        "regenerationUptime": 78.5119,
        "resPerMinute": 0.04329004329004329,
        "resistancePerSecond": 0.33926601731601735,
        "ripsInPerMinute": 19.653679653679653,
        "riteUptime": 28.3683,
        "score": 83.75467037930684,
        "stabilityPerSecond": 0.9591544011544011,
        "surviveRatio": 80.72218986604543
    },
    {
        "appliedCrowdControlPerMinute": 2.014483212639895,
        "blockPerMinute": 32.745227123107306,
        "cleansesInPerMinute": 39.815668202764975,
        "deathPerMinute": 0.10483401281304601,
        "deathRatio": 18.75,
        "downPerMinute": 0.27955736750145604,
        "durationInCombat": 1519,
        "evadePerMinute": 112.96905859117841,
        "id": "爱梅特塞尔克.7563",
        "opScore": 0.0,
        "profession": "裁决",
        "quicknessPerSecond": 0.0,
        "regenerationUptime": 76.1212,
        "resPerMinute": 0.07899934167215274,
        "resistancePerSecond": 0.3510511520737327,
        "ripsInPerMinute": 21.40882159315339,
        "riteUptime": 26.3893,
        "score": 80.88976744609054,
        "stabilityPerSecond": 0.8872350230414745,
        "surviveRatio": 88.46825859056494
    },
    {
        "appliedCrowdControlPerMinute": 3.819935691318328,
        "blockPerMinute": 80.29581993569131,
        "cleansesInPerMinute": 39.12540192926045,
        "deathPerMinute": 0.15487867836861127,
        "deathRatio": 27.77777777777778,
        "downPerMinute": 0.3407330924109448,
        "durationInCombat": 1555,
        "evadePerMinute": 118.53376205787781,
        "id": "wanglei.2043",
        "opScore": 0.0,
        "profession": "裁决",
        "quicknessPerSecond": 0.0,
        "regenerationUptime": 91.1092,
        "resPerMinute": 0.270096463022508,
        "resistancePerSecond": 0.3934420578778135,
        "ripsInPerMinute": 13.42765273311897,
        "riteUptime": 28.2432,
        "score": 80.19517827875742,
        "stabilityPerSecond": 1.1405665594855305,
        "surviveRatio": 80.2787816210635
    },
    {
        "appliedCrowdControlPerMinute": 4.709302325581396,
        "blockPerMinute": 14.127906976744185,
        "cleansesInPerMinute": 37.325581395348834,
        "deathPerMinute": 0.0,
        "deathRatio": 0.0,
        "downPerMinute": 0.1680672268907563,
        "durationInCombat": 344,
        "evadePerMinute": 43.77906976744186,
        "id": "曾讨厌.6421",
        "opScore": 0.0,
        "profession": "裁决",
        "quicknessPerSecond": 0.0,
        "regenerationUptime": 90.2719,
        "resPerMinute": 0.0,
        "resistancePerSecond": 0.25199709302325585,
        "ripsInPerMinute": 17.093023255813954,
        "riteUptime": 21.7441,
        "score": 72.80542274607518,
        "stabilityPerSecond": 0.8987412790697674,
        "surviveRatio": 96.35854341736695
    },
    {
        "appliedCrowdControlPerMinute": 0.8849557522123893,
        "blockPerMinute": 12.477876106194689,
        "cleansesInPerMinute": 29.469026548672563,
        "deathPerMinute": 0.0,
        "deathRatio": 0.0,
        "downPerMinute": 0.0,
        "durationInCombat": 678,
        "evadePerMinute": 31.592920353982297,
        "id": "宇宙UpUp.7123",
        "opScore": 0.0,
        "profession": "裁决",
        "quicknessPerSecond": 0.0,
        "regenerationUptime": 0.0,
        "resPerMinute": 0.0,
        "resistancePerSecond": 0.2124424778761062,
        "ripsInPerMinute": 16.46017699115044,
        "riteUptime": 0.0,
        "score": 61.28780235988201,
        "stabilityPerSecond": 0.858976401179941,
        "surviveRatio": 98.40348330914368
    },
    {
        "appliedCrowdControlPerMinute": 0.6989576946658491,
        "blockPerMinute": 11.992642550582465,
        "cleansesInPerMinute": 83.47026364193746,
        "deathPerMinute": 0.030975735673722252,
        "deathRatio": 5.555555555555555,
        "downPerMinute": 0.030975735673722252,
        "durationInCombat": 1631,
        "evadePerMinute": 39.141630901287556,
        "id": "上弦月.8934",
        "opScore": 0.0,
        "profession": "圣言",
        "quicknessPerSecond": 0.4612674432863273,
        "regenerationUptime": 93.5822,
        "resPerMinute": 3.347639484978541,
        "resistancePerSecond": 0.5900754138565297,
        "ripsInPerMinute": 1.8025751072961373,
        "riteUptime": 27.1218,
        "score": 91.1594990831676,
        "stabilityPerSecond": 1.4841594114040468,
        "surviveRatio": 84.20237480640165
    },
    {
        "appliedCrowdControlPerMinute": 0.5610753945061367,
        "blockPerMinute": 7.364114552893045,
        "cleansesInPerMinute": 34.19053185271771,
        "deathPerMinute": 0.030975735673722252,
        "deathRatio": 5.555555555555555,
        "downPerMinute": 0.09292720702116676,
        "durationInCombat": 1711,
        "evadePerMinute": 30.22793687901812,
        "id": "罗伯特与克里斯汀.6417",
        "opScore": 0.0,
        "profession": "圣言",
        "quicknessPerSecond": 0.3217048509643484,
        "regenerationUptime": 90.9543,
        "resPerMinute": 1.157218001168907,
        "resistancePerSecond": 0.44588264172998254,
        "ripsInPerMinute": 0.03506721215663355,
        "riteUptime": 34.6761,
        "score": 83.9814248693579,
        "stabilityPerSecond": 1.0520216247808298,
        "surviveRatio": 88.33247289623128
    },
    {
        "appliedCrowdControlPerMinute": 0.759493670886076,
        "blockPerMinute": 126.83544303797468,
        "cleansesInPerMinute": 28.860759493670887,
        "deathPerMinute": 0.0,
        "deathRatio": 0.0,
        "downPerMinute": 0.0,
        "durationInCombat": 79,
        "evadePerMinute": 31.89873417721519,
        "id": "长期速逝.2587",
        "opScore": 0.0,
        "profession": "圣言",
        "quicknessPerSecond": 0.3687759493670886,
        "regenerationUptime": 94.903,
        "resPerMinute": 0.0,
        "resistancePerSecond": 0.18398227848101265,
        "ripsInPerMinute": 0.0,
        "riteUptime": 24.768,
        "score": 82.18155696202531,
        "stabilityPerSecond": 0.9504683544303798,
        "surviveRatio": 97.53086419753086
    },
    {
        "appliedCrowdControlPerMinute": 0.9694171956145413,
        "blockPerMinute": 13.017888055395268,
        "cleansesInPerMinute": 52.10617426428159,
        "deathPerMinute": 0.030975735673722252,
        "deathRatio": 5.555555555555555,
        "downPerMinute": 0.12390294269488901,
        "durationInCombat": 1733,
        "evadePerMinute": 14.610502019619158,
        "id": "李献计.6703",
        "opScore": 0.0,
        "profession": "圣言",
        "quicknessPerSecond": 0.33572954414310446,
        "regenerationUptime": 85.4209,
        "resPerMinute": 0.415464512406232,
        "resistancePerSecond": 0.4322215233698788,
        "ripsInPerMinute": 0.103866128101558,
        "riteUptime": 27.5175,
        "score": 82.03360935510115,
        "stabilityPerSecond": 1.230124639353722,
        "surviveRatio": 89.46824987093443
    },
    {
        "appliedCrowdControlPerMinute": 0.9842271293375394,
        "blockPerMinute": 52.921135646687695,
        "cleansesInPerMinute": 30.73817034700315,
        "deathPerMinute": 0.061951471347444505,
        "deathRatio": 11.11111111111111,
        "downPerMinute": 0.21683014971605577,
        "durationInCombat": 1585,
        "evadePerMinute": 35.73501577287066,
        "id": "得意阳阳.6082",
        "opScore": 0.0,
        "profession": "圣言",
        "quicknessPerSecond": 0.26811034700315456,
        "regenerationUptime": 84.9505,
        "resPerMinute": 0.8706624605678233,
        "resistancePerSecond": 0.3628381703470031,
        "ripsInPerMinute": 0.3028391167192429,
        "riteUptime": 19.0499,
        "score": 80.03838601976997,
        "stabilityPerSecond": 0.7983072555205049,
        "surviveRatio": 81.82756840474961
    },
    {
        "appliedCrowdControlPerMinute": 0.7364341085271318,
        "blockPerMinute": 18.13953488372093,
        "cleansesInPerMinute": 31.744186046511626,
        "deathPerMinute": 0.061951471347444505,
        "deathRatio": 11.11111111111111,
        "downPerMinute": 0.12390294269488901,
        "durationInCombat": 1548,
        "evadePerMinute": 33.72093023255814,
        "id": "Miul.1235",
        "opScore": 0.0,
        "profession": "圣言",
        "quicknessPerSecond": 0.3941875322997416,
        "regenerationUptime": 86.321,
        "resPerMinute": 0.3488372093023256,
        "resistancePerSecond": 0.3716242894056848,
        "ripsInPerMinute": 0.19379844961240308,
        "riteUptime": 23.9484,
        "score": 79.2100528348401,
        "stabilityPerSecond": 1.0145103359173127,
        "surviveRatio": 79.9173980382034
    },
    {
        "appliedCrowdControlPerMinute": 0.8492569002123141,
        "blockPerMinute": 12.356687898089172,
        "cleansesInPerMinute": 49.34182590233546,
        "deathPerMinute": 0.06988934187536401,
        "deathRatio": 12.5,
        "downPerMinute": 0.10483401281304601,
        "durationInCombat": 1413,
        "evadePerMinute": 46.28450106157112,
        "id": "三世道长.5328",
        "opScore": 0.0,
        "profession": "圣言",
        "quicknessPerSecond": 0.29927048832271763,
        "regenerationUptime": 84.6424,
        "resPerMinute": 0.21231422505307854,
        "resistancePerSecond": 0.31705506015569707,
        "ripsInPerMinute": 0.08492569002123142,
        "riteUptime": 23.9283,
        "score": 77.79643000410944,
        "stabilityPerSecond": 0.9905152158527956,
        "surviveRatio": 82.29470005824112
    },
    {
        "appliedCrowdControlPerMinute": 0.6854531607006855,
        "blockPerMinute": 27.692307692307693,
        "cleansesInPerMinute": 35.36938309215537,
        "deathPerMinute": 0.07717041800643086,
        "deathRatio": 13.333333333333334,
        "downPerMinute": 0.270096463022508,
        "durationInCombat": 1313,
        "evadePerMinute": 34.272658035034276,
        "id": "我特有.2043",
        "opScore": 0.0,
        "profession": "圣言",
        "quicknessPerSecond": 0.30508134044173646,
        "regenerationUptime": 89.9139,
        "resPerMinute": 0.2284843869002285,
        "resistancePerSecond": 0.39781622239146996,
        "ripsInPerMinute": 0.0,
        "riteUptime": 24.4009,
        "score": 75.75896021481941,
        "stabilityPerSecond": 1.0426923076923076,
        "surviveRatio": 84.43729903536978
    },
    {
        "appliedCrowdControlPerMinute": 0.20055710306406685,
        "blockPerMinute": 7.688022284122562,
        "cleansesInPerMinute": 121.30362116991643,
        "deathPerMinute": 0.0,
        "deathRatio": 0.0,
        "downPerMinute": 0.0,
        "durationInCombat": 1795,
        "evadePerMinute": 23.532033426183844,
        "id": "落英梦.2473",
        "opScore": 0.0,
        "profession": "奶德",
        "quicknessPerSecond": 0.12017359331476322,
        "regenerationUptime": 92.2273,
        "resPerMinute": 1.3704735376044568,
        "resistancePerSecond": 0.06374991643454038,
        "ripsInPerMinute": 0.8356545961002785,
        "riteUptime": 23.8727,
        "score": 94.26072423398328,
        "stabilityPerSecond": 0.0,
        "surviveRatio": 92.6690758905524
    },
    {
        "appliedCrowdControlPerMinute": 0.1195219123505976,
        "blockPerMinute": 4.382470119521912,
        "cleansesInPerMinute": 111.27490039840637,
        "deathPerMinute": 0.09292720702116676,
        "deathRatio": 16.666666666666668,
        "downPerMinute": 0.15487867836861127,
        "durationInCombat": 1506,
        "evadePerMinute": 30.677290836653384,
        "id": "ZanTtttt.5938",
        "opScore": 0.0,
        "profession": "奶德",
        "quicknessPerSecond": 0.06315405046480743,
        "regenerationUptime": 90.7504,
        "resPerMinute": 0.1195219123505976,
        "resistancePerSecond": 0.09195690571049132,
        "ripsInPerMinute": 0.7171314741035856,
        "riteUptime": 27.8985,
        "score": 86.05983294493683,
        "stabilityPerSecond": 0.0,
        "surviveRatio": 77.74909654104285
    },
    {
        "appliedCrowdControlPerMinute": 0.0,
        "blockPerMinute": 4.296296296296297,
        "cleansesInPerMinute": 103.33333333333333,
        "deathPerMinute": 0.06263048016701461,
        "deathRatio": 11.11111111111111,
        "downPerMinute": 0.12526096033402923,
        "durationInCombat": 810,
        "evadePerMinute": 46.22222222222222,
        "id": "风之野子.2345",
        "opScore": 0.0,
        "profession": "奶德",
        "quicknessPerSecond": 0.0,
        "regenerationUptime": 91.4154,
        "resPerMinute": 0.2962962962962963,
        "resistancePerSecond": 0.08214345679012347,
        "ripsInPerMinute": 0.4444444444444444,
        "riteUptime": 20.3698,
        "score": 85.6562282533055,
        "stabilityPerSecond": 0.0,
        "surviveRatio": 84.55114822546973
    },
    {
        "appliedCrowdControlPerMinute": 0.27044430135222153,
        "blockPerMinute": 9.388280746941405,
        "cleansesInPerMinute": 105.55054732775274,
        "deathPerMinute": 0.12875536480686695,
        "deathRatio": 23.529411764705884,
        "downPerMinute": 0.22532188841201717,
        "durationInCombat": 1553,
        "evadePerMinute": 35.660012878300066,
        "id": "DIO.7246",
        "opScore": 0.0,
        "profession": "奶德",
        "quicknessPerSecond": 0.04330972311654861,
        "regenerationUptime": 86.9161,
        "resPerMinute": 0.42498390212491954,
        "resistancePerSecond": 0.044336445589182226,
        "ripsInPerMinute": 0.46361880231809405,
        "riteUptime": 35.3134,
        "score": 81.0692672624032,
        "stabilityPerSecond": 0.0,
        "surviveRatio": 83.31545064377683
    },
    {
        "appliedCrowdControlPerMinute": 0.08130081300813008,
        "blockPerMinute": 9.268292682926829,
        "cleansesInPerMinute": 100.52845528455283,
        "deathPerMinute": 0.12390294269488901,
        "deathRatio": 22.22222222222222,
        "downPerMinute": 0.37170882808466704,
        "durationInCombat": 1476,
        "evadePerMinute": 38.048780487804876,
        "id": "剑鬼丶.7902",
        "opScore": 0.0,
        "profession": "奶德",
        "quicknessPerSecond": 0.010378726287262873,
        "regenerationUptime": 85.9445,
        "resPerMinute": 0.6910569105691057,
        "resistancePerSecond": 0.06458136856368564,
        "ripsInPerMinute": 0.8130081300813008,
        "riteUptime": 17.8096,
        "score": 73.88550460019056,
        "stabilityPerSecond": 0.0,
        "surviveRatio": 76.20030975735673
    },
    {
        "appliedCrowdControlPerMinute": 0.0,
        "blockPerMinute": 5.5,
        "cleansesInPerMinute": 26.5,
        "deathPerMinute": 0.27272727272727276,
        "deathRatio": 50.0,
        "downPerMinute": 1.090909090909091,
        "durationInCombat": 120,
        "evadePerMinute": 10.0,
        "id": "reesoon.5981",
        "opScore": 0.0,
        "profession": "奶德",
        "quicknessPerSecond": 0.0,
        "regenerationUptime": 63.7216,
        "resPerMinute": 0.0,
        "resistancePerSecond": 0.0,
        "ripsInPerMinute": 0.0,
        "riteUptime": 0.0,
        "score": 26.540533333333336,
        "stabilityPerSecond": 0.0,
        "surviveRatio": 54.54545454545455
    },
    {
        "appliedCrowdControlPerMinute": 5.916897506925208,
        "blockPerMinute": 9.506925207756233,
        "cleansesInPerMinute": 67.04709141274239,
        "deathPerMinute": 0.0,
        "deathRatio": 0.0,
        "downPerMinute": 0.0,
        "durationInCombat": 1805,
        "evadePerMinute": 11.90027700831025,
        "id": "但为君故.3846",
        "opScore": 0.0,
        "profession": "元晶",
        "quicknessPerSecond": 0.26664858725761775,
        "regenerationUptime": 92.4682,
        "resPerMinute": 0.3988919667590028,
        "resistancePerSecond": 0.30486853185595564,
        "ripsInPerMinute": 2.260387811634349,
        "riteUptime": 24.836,
        "score": 100.0,
        "stabilityPerSecond": 2.1336991689750695,
        "surviveRatio": 93.18533815178111
    },
    {
        "appliedCrowdControlPerMinute": 5.985915492957747,
        "blockPerMinute": 7.394366197183099,
        "cleansesInPerMinute": 21.232394366197184,
        "deathPerMinute": 0.030975735673722252,
        "deathRatio": 5.555555555555555,
        "downPerMinute": 0.030975735673722252,
        "durationInCombat": 1704,
        "evadePerMinute": 47.147887323943664,
        "id": "我心飞翔.5862",
        "opScore": 0.0,
        "profession": "灾厄",
        "quicknessPerSecond": 0.0,
        "regenerationUptime": 87.3981,
        "resPerMinute": 2.0422535211267605,
        "resistancePerSecond": 0.0,
        "ripsInPerMinute": 71.72535211267606,
        "riteUptime": 27.9094,
        "score": 87.94230860122013,
        "stabilityPerSecond": 0.08152288732394365,
        "surviveRatio": 87.9710893133712
    },
    {
        "appliedCrowdControlPerMinute": 5.401554404145077,
        "blockPerMinute": 5.790155440414508,
        "cleansesInPerMinute": 37.189119170984455,
        "deathPerMinute": 0.12390294269488901,
        "deathRatio": 22.22222222222222,
        "downPerMinute": 0.2787816210635003,
        "durationInCombat": 1544,
        "evadePerMinute": 44.22279792746114,
        "id": "泰坦ii.8036",
        "opScore": 0.0,
        "profession": "灾厄",
        "quicknessPerSecond": 0.010680375647668394,
        "regenerationUptime": 84.0211,
        "resPerMinute": 0.699481865284974,
        "resistancePerSecond": 0.0,
        "ripsInPerMinute": 85.88082901554404,
        "riteUptime": 27.9003,
        "score": 82.02554862896257,
        "stabilityPerSecond": 0.17157059585492226,
        "surviveRatio": 79.71089313371192
    },
    {
        "appliedCrowdControlPerMinute": 5.442477876106195,
        "blockPerMinute": 7.831858407079646,
        "cleansesInPerMinute": 30.530973451327434,
        "deathPerMinute": 0.21238938053097348,
        "deathRatio": 50.0,
        "downPerMinute": 0.42477876106194695,
        "durationInCombat": 452,
        "evadePerMinute": 50.97345132743363,
        "id": "九七年的特仑苏.2934",
        "opScore": 0.0,
        "profession": "灾厄",
        "quicknessPerSecond": 0.0,
        "regenerationUptime": 68.425,
        "resPerMinute": 1.1946902654867257,
        "resistancePerSecond": 0.0,
        "ripsInPerMinute": 97.16814159292035,
        "riteUptime": 20.3402,
        "score": 77.23451327433628,
        "stabilityPerSecond": 0.09730309734513275,
        "surviveRatio": 80.0
    },
    {
        "appliedCrowdControlPerMinute": 5.087378640776699,
        "blockPerMinute": 8.970873786407767,
        "cleansesInPerMinute": 16.737864077669904,
        "deathPerMinute": 0.06437768240343347,
        "deathRatio": 11.764705882352942,
        "downPerMinute": 0.3218884120171674,
        "durationInCombat": 1545,
        "evadePerMinute": 22.25242718446602,
        "id": "leangiap.9476",
        "opScore": 0.0,
        "profession": "灾厄",
        "quicknessPerSecond": 0.0,
        "regenerationUptime": 83.7104,
        "resPerMinute": 0.970873786407767,
        "resistancePerSecond": 0.0,
        "ripsInPerMinute": 76.15533980582525,
        "riteUptime": 16.2858,
        "score": 71.83967387530036,
        "stabilityPerSecond": 0.07855922330097087,
        "surviveRatio": 82.8862660944206
    },
    {
        "appliedCrowdControlPerMinute": 2.246696035242291,
        "blockPerMinute": 7.400881057268723,
        "cleansesInPerMinute": 15.066079295154186,
        "deathPerMinute": 0.08746355685131195,
        "deathRatio": 20.0,
        "downPerMinute": 0.08746355685131195,
        "durationInCombat": 454,
        "evadePerMinute": 25.24229074889868,
        "id": "你赐的殇心.1436",
        "opScore": 0.0,
        "profession": "灾厄",
        "quicknessPerSecond": 0.0,
        "regenerationUptime": 45.6461,
        "resPerMinute": 0.7929515418502203,
        "resistancePerSecond": 0.0,
        "ripsInPerMinute": 34.36123348017621,
        "riteUptime": 5.599,
        "score": 59.32084098585942,
        "stabilityPerSecond": 0.11429735682819382,
        "surviveRatio": 66.1807580174927
    },
    {
        "appliedCrowdControlPerMinute": 3.771186440677966,
        "blockPerMinute": 6.398305084745762,
        "cleansesInPerMinute": 13.177966101694915,
        "deathPerMinute": 0.18585441404233352,
        "deathRatio": 33.333333333333336,
        "downPerMinute": 0.4026845637583893,
        "durationInCombat": 1416,
        "evadePerMinute": 38.728813559322035,
        "id": "扭扭胯胯肘.8140",
        "opScore": 0.0,
        "profession": "灾厄",
        "quicknessPerSecond": 0.003578460451977401,
        "regenerationUptime": 80.2589,
        "resPerMinute": 0.211864406779661,
        "resistancePerSecond": 0.0,
        "ripsInPerMinute": 54.15254237288135,
        "riteUptime": 15.6665,
        "score": 55.19558355135934,
        "stabilityPerSecond": 0.05993220338983051,
        "surviveRatio": 73.10273618998451
    },
    {
        "appliedCrowdControlPerMinute": 0.8888888888888888,
        "blockPerMinute": 46.888888888888886,
        "cleansesInPerMinute": 122.11111111111111,
        "deathPerMinute": 0.0907715582450832,
        "deathRatio": 20.0,
        "downPerMinute": 0.0907715582450832,
        "durationInCombat": 540,
        "evadePerMinute": 40.55555555555556,
        "id": "别吵了.1650",
        "opScore": 0.0,
        "profession": "圣辉",
        "quicknessPerSecond": 0.3728818518518518,
        "regenerationUptime": 83.8991,
        "resPerMinute": 0.4444444444444444,
        "resistancePerSecond": 0.16465666666666667,
        "ripsInPerMinute": 0.7777777777777778,
        "riteUptime": 1.7304,
        "score": 85.54937655908556,
        "stabilityPerSecond": 2.700788888888889,
        "surviveRatio": 81.69440242057489
    },
    {
        "appliedCrowdControlPerMinute": 4.2582897033158815,
        "blockPerMinute": 20.418848167539267,
        "cleansesInPerMinute": 49.075043630017454,
        "deathPerMinute": 0.030975735673722252,
        "deathRatio": 5.555555555555555,
        "downPerMinute": 0.15487867836861127,
        "durationInCombat": 1719,
        "evadePerMinute": 29.9825479930192,
        "id": "阿尔比雷欧.2487",
        "opScore": 0.0,
        "profession": "圣辉",
        "quicknessPerSecond": 0.1315321698662013,
        "regenerationUptime": 82.5138,
        "resPerMinute": 0.06980802792321117,
        "resistancePerSecond": 0.2404609656777196,
        "ripsInPerMinute": 1.012216404886562,
        "riteUptime": 14.6754,
        "score": 75.65087826762127,
        "stabilityPerSecond": 2.353457824316463,
        "surviveRatio": 88.74548270521424
    },
    {
        "deathPerMinute": 0.0,
        "deathRatio": 0.0,
        "dmgPerSecond": 4532.2525773195875,
        "downPerMinute": 0.0,
        "downsPerMinute": 2.934782608695652,
        "durationInCombat": 184,
        "id": "风之野子.2345",
        "opScore": 0.0,
        "profession": "魂兽",
        "score": 99.26361497086509,
        "surviveRatio": 94.84536082474227
    },
    {
        "deathPerMinute": 0.0,
        "deathRatio": 0.0,
        "dmgPerSecond": 787.8633720930233,
        "downPerMinute": 0.0,
        "downsPerMinute": 0.0,
        "durationInCombat": 47,
        "id": "剑鬼丶.7902",
        "opScore": 0.0,
        "profession": "魂兽",
        "score": 58.56373230535895,
        "surviveRatio": 13.662790697674419
    },
    {
        "deathPerMinute": 0.0,
        "deathRatio": 0.0,
        "dmgPerSecond": 5595.394736842105,
        "downPerMinute": 0.0,
        "downsPerMinute": 0.29126213592233013,
        "durationInCombat": 206,
        "id": "别吵了.1650",
        "opScore": 0.0,
        "profession": "守护",
        "score": 100.0,
        "surviveRatio": 67.76315789473684
    },
    {
        "deathPerMinute": 0.0,
        "deathRatio": 0.0,
        "dmgPerSecond": 6274.040784718637,
        "downPerMinute": 0.061951471347444505,
        "downsPerMinute": 2.09695603156708,
        "durationInCombat": 1774,
        "id": "kssws.2315",
        "opScore": 0.0,
        "profession": "全息",
        "score": 96.90242643262778,
        "surviveRatio": 91.58492514197212
    },
    {
        "deathPerMinute": 0.0,
        "deathRatio": 0.0,
        "dmgPerSecond": 5957.838409912235,
        "downPerMinute": 0.061951471347444505,
        "downsPerMinute": 1.631728045325779,
        "durationInCombat": 1765,
        "id": "李知花.2590",
        "opScore": 0.0,
        "profession": "全息",
        "score": 96.90242643262778,
        "surviveRatio": 91.1202891068663
    },
    {
        "deathPerMinute": 0.1609442060085837,
        "deathRatio": 29.41176470588235,
        "dmgPerSecond": 4653.496244635193,
        "downPerMinute": 0.28969957081545067,
        "downsPerMinute": 1.7073170731707317,
        "durationInCombat": 1476,
        "id": "xiaoying.1704",
        "opScore": 0.0,
        "profession": "全息",
        "score": 85.51502145922747,
        "surviveRatio": 79.18454935622317
    },
    {
        "deathPerMinute": 0.12390294269488901,
        "deathRatio": 22.22222222222222,
        "dmgPerSecond": 4062.358286009293,
        "downPerMinute": 0.21683014971605577,
        "downsPerMinute": 1.6563146997929608,
        "durationInCombat": 1449,
        "id": "路丶瑶.6341",
        "opScore": 0.0,
        "profession": "全息",
        "score": 83.31456084038518,
        "surviveRatio": 74.80640165203924
    },
    {
        "deathPerMinute": 0.061951471347444505,
        "deathRatio": 11.11111111111111,
        "dmgPerSecond": 6172.018069179143,
        "downPerMinute": 0.15487867836861127,
        "downsPerMinute": 1.2834224598930482,
        "durationInCombat": 1683,
        "id": "SSR.2504",
        "opScore": 0.0,
        "profession": "暴风",
        "score": 92.25606608156943,
        "surviveRatio": 86.88693856479091
    },
    {
        "deathPerMinute": 0.0,
        "deathRatio": 0.0,
        "dmgPerSecond": 6513.681818181818,
        "downPerMinute": 0.0,
        "downsPerMinute": 1.9178082191780823,
        "durationInCombat": 219,
        "id": "大灰狼.2538",
        "opScore": 0.0,
        "profession": "猎龙",
        "score": 100.0,
        "surviveRatio": 99.54545454545455
    },
    {
        "deathPerMinute": 0.0,
        "deathRatio": 0.0,
        "dmgPerSecond": 6588.095890410959,
        "downPerMinute": 0.0,
        "downsPerMinute": 1.7647058823529411,
        "durationInCombat": 68,
        "id": "yokie.9781",
        "opScore": 0.0,
        "profession": "猎龙",
        "score": 100.0,
        "surviveRatio": 93.15068493150685
    },
    {
        "deathPerMinute": 0.0,
        "deathRatio": 0.0,
        "dmgPerSecond": 4562.29647887324,
        "downPerMinute": 0.0,
        "downsPerMinute": 1.4759358288770053,
        "durationInCombat": 935,
        "id": "别吵了.1650",
        "opScore": 0.0,
        "profession": "猎龙",
        "score": 99.5901791181874,
        "surviveRatio": 65.84507042253522
    },
    {
        "deathPerMinute": 0.061951471347444505,
        "deathRatio": 11.11111111111111,
        "dmgPerSecond": 5796.474961280331,
        "downPerMinute": 0.09292720702116676,
        "downsPerMinute": 1.747941735275491,
        "durationInCombat": 1579,
        "id": "卿晓之.4786",
        "opScore": 0.0,
        "profession": "猎龙",
        "score": 95.35363964894167,
        "surviveRatio": 81.51781104801239
    },
    {
        "deathPerMinute": 0.09895547003848268,
        "deathRatio": 17.647058823529413,
        "dmgPerSecond": 4970.751511819682,
        "downPerMinute": 0.09895547003848268,
        "downsPerMinute": 1.5206372194062274,
        "durationInCombat": 1381,
        "id": "希丶灵.8762",
        "opScore": 0.0,
        "profession": "猎龙",
        "score": 95.05222649807587,
        "surviveRatio": 75.92083562396921
    },
    {
        "deathPerMinute": 0.09292720702116676,
        "deathRatio": 16.666666666666668,
        "dmgPerSecond": 5061.864739287558,
        "downPerMinute": 0.24780588538977802,
        "downsPerMinute": 1.3539651837524178,
        "durationInCombat": 1551,
        "id": "吃肉的流氓兔.6078",
        "opScore": 0.0,
        "profession": "猎龙",
        "score": 87.60970573051111,
        "surviveRatio": 80.07227671657202
    },
    {
        "deathPerMinute": 0.12390294269488901,
        "deathRatio": 22.22222222222222,
        "dmgPerSecond": 5592.28600929272,
        "downPerMinute": 0.2787816210635003,
        "downsPerMinute": 1.5879017013232515,
        "durationInCombat": 1587,
        "id": "西亿欧丶.4871",
        "opScore": 0.0,
        "profession": "猎龙",
        "score": 86.06091894682498,
        "surviveRatio": 81.93082085699535
    },
    {
        "deathPerMinute": 0.0,
        "deathRatio": 0.0,
        "dmgPerSecond": 5233.931818181818,
        "downPerMinute": 0.5454545454545455,
        "downsPerMinute": 0.2777777777777778,
        "durationInCombat": 216,
        "id": "九七年的特仑苏.2934",
        "opScore": 0.0,
        "profession": "猎龙",
        "score": 72.72727272727272,
        "surviveRatio": 98.18181818181819
    }
]